worddfn/__init__.py
worddfn/__main__.py
worddfn/dictionaryAPI.py
worddfn/setting.py
worddfn-0.1.9.dist-info/METADATA
worddfn-0.1.9.dist-info/WHEEL
worddfn-0.1.9.dist-info/entry_points.txt
worddfn-0.1.9.dist-info/licenses/LICENSE
worddfn-0.1.9.dist-info/RECORD
