Metadata-Version: 2.1
Name: worddfn
Version: 0.1.9
Summary: worddfn, lookup word meaning and forms via the wordnik api
Project-URL: Homepage, https://github.com/SirX7/wordDFN
Project-URL: Bug Tracker, https://github.com/SirX7/wordDFN/issues
Author-email: Shall Mcfield <xhall.mc@protonmail.com>
License: MIT
License-File: LICENSE
Classifier: Development Status :: 4 - Beta
Classifier: Environment :: Console
Classifier: Intended Audience :: Education
Classifier: Intended Audience :: Information Technology
Classifier: Intended Audience :: Science/Research
Classifier: License :: OSI Approved :: MIT License
Classifier: Operating System :: OS Independent
Classifier: Programming Language :: Python
Classifier: Programming Language :: Python :: 3
Classifier: Programming Language :: Python :: 3 :: Only
Classifier: Programming Language :: Python :: 3.8
Classifier: Programming Language :: Python :: 3.9
Classifier: Programming Language :: Python :: 3.10
Classifier: Programming Language :: Python :: 3.11
Classifier: Topic :: Education
Classifier: Topic :: Internet
Requires-Python: >=3.8
Requires-Dist: pyperclip==1.8.2
Requires-Dist: requests>=2.31.0
